jsonizable/__init__.py
jsonizable/common.py
jsonizable/exceptions.py
jsonizable/jsonizable.py
jsonizable/read.py
jsonizable/write.py
jsonizable-1.0.4.dist-info/LICENSE
jsonizable-1.0.4.dist-info/METADATA
jsonizable-1.0.4.dist-info/WHEEL
jsonizable-1.0.4.dist-info/top_level.txt
jsonizable-1.0.4.dist-info/RECORD
